MANIFEST.in
README.md
package_info.json
requirements.txt
setup.py
th2/data_services/utils/rpt_viewer/__init__.py
th2/data_services/utils/rpt_viewer/th2_gui_report.py
th2_data_services_utils_rpt_viewer.egg-info/PKG-INFO
th2_data_services_utils_rpt_viewer.egg-info/SOURCES.txt
th2_data_services_utils_rpt_viewer.egg-info/dependency_links.txt
th2_data_services_utils_rpt_viewer.egg-info/top_level.txt