Metadata-Version: 2.1
Name: th2-data-services-utils-rpt-viewer
Version: 5.0.1.0.dev4142341936
Summary: th2_data_services_utils_rpt_viewer
Home-page: https://github.com/th2-net/th2-data-services-utils
Author: TH2-devs
Author-email: th2-devs@exactprosystems.com
License: Apache License 2.0
Platform: UNKNOWN
Requires-Python: >=3.7
